lab3/lab3.v
module PAT(clk, reset, data, flag);
    input clk, reset, data;
    output reg flag;
    reg [2:0] state;
    reg [2:0] next_state;
    initial begin
        state = 3'b000;
        next_state = 3'b000;
    end
    always@(posedge clk)begin
        if(reset)
            state <= 3'b000;
        else
            state <= next_state;
    end

    always@(*)begin
        if(reset) begin
            next_state = 3'b000;
            flag = 1'b0;
        end
        else begin
        case(state)
            3'b000:begin
                if(data)
                    next_state = 3'b001;
                else
                    next_state = 3'b000;
            end
            3'b001:begin
                if(data)
                    next_state = 3'b011;
                else
                    next_state = 3'b010;
            end
            3'b010:begin
                if(data)
                    next_state = 3'b101;
                else
                    next_state = 3'b000;
            end
            3'b011:begin
                if(data)
                    next_state = 3'b011;
                else
                    next_state = 3'b110;
            end
            3'b101:begin
                if(data)
                    next_state = 3'b011;
                else
                    next_state = 3'b010;
            end
            3'b110:begin
                if(data)
                    next_state = 3'b101;
                else
                    next_state = 3'b000;
            end
            default:begin
                next_state = 3'b000;
            end
        endcase
        end
    end

    always@(posedge clk)begin
        if(reset)
            flag = 1'b0;
        else begin
            case(state)
                3'b110:begin
                    if(data)
                        flag = 1'b1;
                    else
                        flag = 1'b0;
                end
                3'b101:begin
                    if(data)
                        flag = 1'b1;
                    else
                        flag = 1'b0;
                end
                default:begin
                    flag = 1'b0;
                end
            endcase
        end
    end
endmodule


module Traffic_Light_Controller(CLK, RESET, LR_has_Car, HW_light, LR_light);
    input CLK, RESET, LR_has_Car;
    output reg [2:0] HW_light, LR_light;
    integer i;
    reg [2:0] state;
    initial begin
        state = 3'b000;
        i = 5;
    end
    always@(*) begin
        if(RESET) begin
            state = 3'b000;
            HW_light = 3'b100;
            LR_light = 3'b001;
            i = 5;
        end
        else begin
            case(state)
                3'b000: begin
                    HW_light = 3'b100;
                    LR_light = 3'b001;
                end
                3'b001: begin
                    HW_light = 3'b010;
                    LR_light = 3'b001;
                end
                3'b010: begin
                    HW_light = 3'b001;
                    LR_light = 3'b001;
                end
                3'b100: begin
                    HW_light = 3'b001;
                    LR_light = 3'b100;
                end
                3'b101: begin
                    HW_light = 3'b001;
                    LR_light = 3'b010;
                end
                3'b110: begin
                    HW_light = 3'b001;
                    LR_light = 3'b001;
                end
            endcase
        end
    end
    always@(posedge CLK && !RESET)begin
        if(i == 0) begin
            case(state)
                3'b000:begin
                    if(LR_has_Car) begin
                        state <= 3'b001;
                        i = 2;
                    end
                end
                3'b001:begin
                    state <= 3'b010;
                end
                3'b010:begin
                    state <= 3'b100;
                    i = 4;
                end
                3'b100:begin
                    state <= 3'b101;
                    i = 2;
                end
                3'b101:begin
                    state <= 3'b110;
                end
                3'b110:begin
                    state <= 3'b000;
                    i = 4;
                end
                default:begin
                    state <= 3'b000;
                    i = 4;
                end
            endcase
        end
        else i = i - 1;
    end
endmodule

lab3/lab3_tb2_vcd.v
`include "lab3.v"

module lab3_tb2;
    reg CLK, RESET, LR_has_Car;
    wire [2:0] HW_light, LR_light;
    parameter delay = 5;
    integer i;
    Traffic_Light_Controller TLC_Lab3(CLK, RESET, LR_has_Car, HW_light, LR_light);
    reg [19:0] LR_pattern = 20'b11111100111111100000;
    initial begin
        $dumpfile("lab3_tb2.vcd");
        $dumpvars(0, lab3_tb2);
        CLK = 0;
        RESET = 1;
        LR_has_Car = 0;
        #delay CLK = ~CLK;
        #delay CLK = ~CLK;
        RESET = 0;
        for(i = 0; i < 20; i = i + 1)begin
            LR_has_Car = LR_pattern[i];
            #delay CLK = ~CLK;
            #delay CLK = ~CLK;
        end
        $finish;
    end
endmodule

lab3/lab3_tb2.vcd
$date
	Sat Jun  3 11:27:37 2023
$end
$version
	Icarus Verilog
$end
$timescale
	1s
$end
$scope module lab3_tb2 $end
$var wire 3 ! LR_light [2:0] $end
$var wire 3 " HW_light [2:0] $end
$var reg 1 # CLK $end
$var reg 1 $ LR_has_Car $end
$var reg 20 % LR_pattern [19:0] $end
$var reg 1 & RESET $end
$var integer 32 ' i [31:0] $end
$scope module TLC_Lab3 $end
$var wire 1 # CLK $end
$var wire 1 $ LR_has_Car $end
$var wire 1 & RESET $end
$var reg 3 ( HW_light [2:0] $end
$var reg 3 ) LR_light [2:0] $end
$var reg 3 * state [2:0] $end
$var integer 32 + i [31:0] $end
$upscope $end
$upscope $end
$enddefinitions $end
#0
$dumpvars
b101 +
b0 *
b1 )
b100 (
bx '
1&
b11111100111111100000 %
0$
0#
b100 "
b1 !
$end
#5
1#
#10
b0 '
0&
0#
#15
b100 +
1#
#20
b1 '
0#
#25
b11 +
1#
#30
b10 '
0#
#35
b10 +
1#
#40
b11 '
0#
#45
b1 +
1#
#50
b100 '
0#
#55
b0 +
1#
#60
1$
b101 '
0#
#65
b10 "
b10 (
b1 *
b10 +
1#
#70
b110 '
0#
#75
b1 +
1#
#80
b111 '
0#
#85
b0 +
1#
#90
b1000 '
0#
#95
b1 "
b1 (
b10 *
1#
#100
b1001 '
0#
#105
b100 !
b100 )
b100 *
b100 +
1#
#110
b1010 '
0#
#115
b11 +
1#
#120
b1011 '
0#
#125
b10 +
1#
#130
0$
b1100 '
0#
#135
b1 +
1#
#140
b1101 '
0#
#145
b0 +
1#
#150
1$
b1110 '
0#
#155
b10 !
b10 )
b101 *
b10 +
1#
#160
b1111 '
0#
#165
b1 +
1#
#170
b10000 '
0#
#175
b0 +
1#
#180
b10001 '
0#
#185
b1 !
b1 )
b110 *
1#
#190
b10010 '
0#
#195
b100 "
b100 (
b0 *
b100 +
1#
#200
b10011 '
0#
#205
b11 +
1#
#210
b10100 '
0#
