lab3/lab3.v
module PAT(clk, reset, data, flag);
    input clk, reset, data;
    output reg flag;
    reg [2:0] state;
    reg [2:0] next_state;
    initial begin
        state = 3'b000;
        next_state = 3'b000;
    end
    always@(posedge clk)begin
        if(reset)
            state <= 3'b000;
        else
            state <= next_state;
    end

    always@(*)begin
        if(reset) begin
            next_state = 3'b000;
            flag = 1'b0;
        end
        else begin
        case(state)
            3'b000:begin
                if(data)
                    next_state = 3'b001;
                else
                    next_state = 3'b000;
            end
            3'b001:begin
                if(data)
                    next_state = 3'b011;
                else
                    next_state = 3'b010;
            end
            3'b010:begin
                if(data)
                    next_state = 3'b101;
                else
                    next_state = 3'b000;
            end
            3'b011:begin
                if(data)
                    next_state = 3'b011;
                else
                    next_state = 3'b110;
            end
            3'b101:begin
                if(data)
                    next_state = 3'b011;
                else
                    next_state = 3'b010;
            end
            3'b110:begin
                if(data)
                    next_state = 3'b101;
                else
                    next_state = 3'b000;
            end
            default:begin
                next_state = 3'b000;
            end
        endcase
        end
    end

    always@(posedge clk)begin
        if(reset)
            flag = 1'b0;
        else begin
            case(state)
                3'b110:begin
                    if(data)
                        flag = 1'b1;
                    else
                        flag = 1'b0;
                end
                3'b101:begin
                    if(data)
                        flag = 1'b1;
                    else
                        flag = 1'b0;
                end
                default:begin
                    flag = 1'b0;
                end
            endcase
        end
    end
endmodule


module Traffic_Light_Controller(CLK, RESET, LR_has_Car, HW_light, LR_light);
    input CLK, RESET, LR_has_Car;
    output reg [2:0] HW_light, LR_light;
    integer i;
    reg [2:0] state;
    initial begin
        state = 3'b000;
        i = 5;
    end
    always@(*) begin
        if(RESET) begin
            state = 3'b000;
            HW_light = 3'b100;
            LR_light = 3'b001;
            i = 5;
        end
        else begin
            case(state)
                3'b000: begin
                    HW_light = 3'b100;
                    LR_light = 3'b001;
                end
                3'b001: begin
                    HW_light = 3'b010;
                    LR_light = 3'b001;
                end
                3'b010: begin
                    HW_light = 3'b001;
                    LR_light = 3'b001;
                end
                3'b100: begin
                    HW_light = 3'b001;
                    LR_light = 3'b100;
                end
                3'b101: begin
                    HW_light = 3'b001;
                    LR_light = 3'b010;
                end
                3'b110: begin
                    HW_light = 3'b001;
                    LR_light = 3'b001;
                end
            endcase
        end
    end
    always@(posedge CLK && !RESET)begin
        if(i == 0) begin
            case(state)
                3'b000:begin
                    if(LR_has_Car) begin
                        state <= 3'b001;
                        i = 2;
                    end
                end
                3'b001:begin
                    state <= 3'b010;
                end
                3'b010:begin
                    state <= 3'b100;
                    i = 4;
                end
                3'b100:begin
                    state <= 3'b101;
                    i = 2;
                end
                3'b101:begin
                    state <= 3'b110;
                end
                3'b110:begin
                    state <= 3'b000;
                    i = 4;
                end
                default:begin
                    state <= 3'b000;
                    i = 4;
                end
            endcase
        end
        else i = i - 1;
    end
endmodule

lab3/lab3_tb1_vcd.v
`include "lab3.v"

module lab3_tb1;
    reg clk, reset, data;
    wire flag;
    parameter delay = 5;
    integer i;
    PAT lab3(clk, reset, data, flag);
    reg [11:0] data_pattern = 12'b101101011101;
    reg [11:0] reset_pattern = 12'b010000000001;
    initial begin
        $dumpfile("lab3_tb1.vcd");
        $dumpvars(0, lab3_tb1);
        clk = 0;
        for(i = 0; i < 12; i = i + 1)begin
            data = data_pattern[i];
            reset = reset_pattern[i];
            #delay clk = ~clk;
            #delay clk = ~clk;
        end
        $finish;
    end
endmodule

lab3/lab3_tb1.vcd
$date
	Sat Jun  3 11:16:39 2023
$end
$version
	Icarus Verilog
$end
$timescale
	1s
$end
$scope module lab3_tb1 $end
$var wire 1 ! flag $end
$var reg 1 " clk $end
$var reg 1 # data $end
$var reg 12 $ data_pattern [11:0] $end
$var reg 1 % reset $end
$var reg 12 & reset_pattern [11:0] $end
$var integer 32 ' i [31:0] $end
$scope module lab3 $end
$var wire 1 " clk $end
$var wire 1 # data $end
$var wire 1 % reset $end
$var reg 1 ! flag $end
$var reg 3 ( next_state [2:0] $end
$var reg 3 ) state [2:0] $end
$upscope $end
$upscope $end
$enddefinitions $end
#0
$dumpvars
b0 )
b0 (
b0 '
b10000000001 &
1%
b101101011101 $
1#
0"
0!
$end
#5
1"
#10
0%
0#
b1 '
0"
#15
1"
#20
b1 (
1#
b10 '
0"
#25
b11 (
b1 )
1"
#30
b11 '
0"
#35
b11 )
1"
#40
b100 '
0"
#45
1"
#50
b110 (
0#
b101 '
0"
#55
b0 (
b110 )
1"
#60
b101 (
1#
b110 '
0"
#65
b11 (
b101 )
1!
1"
#70
b10 (
0#
b111 '
0"
#75
b0 (
b10 )
0!
1"
#80
b101 (
1#
b1000 '
0"
#85
b11 (
b101 )
1"
#90
b1001 '
0"
#95
b11 )
1!
1"
#100
0!
b0 (
1%
0#
b1010 '
0"
#105
b0 )
1"
#110
b1 (
0%
1#
b1011 '
0"
#115
b11 (
b1 )
1"
#120
b1100 '
0"
